fsim/bin/fsim
fsim/include/runtime/version.hh.in
fsim/include/runtime/scheduler.cc
fsim/include/runtime/module.cc
fsim/include/runtime/system_task.hh
fsim/include/runtime/CMakeLists.txt
fsim/include/runtime/variable.hh
fsim/include/runtime/variable.cc
fsim/include/runtime/macro.hh
fsim/include/runtime/scheduler.hh
fsim/include/runtime/module.hh
fsim/include/runtime/system_task.cc
fsim/include/runtime/vpi.cc
fsim/include/runtime/vpi.hh
fsim/include/marl/dag.h
fsim/include/marl/ticket.h
fsim/include/marl/task.h
fsim/include/marl/debug.h
fsim/include/marl/export.h
fsim/include/marl/pool.h
fsim/include/marl/parallelize.h
fsim/include/marl/event.h
fsim/include/marl/scheduler.h
fsim/include/marl/conditionvariable.h
fsim/include/marl/sanitizers.h
fsim/include/marl/thread.h
fsim/include/marl/trace.h
fsim/include/marl/waitgroup.h
fsim/include/marl/deprecated.h
fsim/include/marl/memory.h
fsim/include/marl/defer.h
fsim/include/marl/containers.h
fsim/include/marl/mutex.h
fsim/include/marl/blockingcall.h
fsim/include/marl/finally.h
fsim/include/marl/tsa.h
fsim/include/logic/bit.hh
fsim/include/logic/struct.hh
fsim/include/logic/union.hh
fsim/include/logic/big_num.hh
fsim/include/logic/array.hh
fsim/include/logic/logic.hh
fsim/include/logic/util.hh
fsim/lib/libfsim-runtime.so
fsim-0.0.5.dist-info/RECORD
fsim-0.0.5.dist-info/LICENSE
fsim-0.0.5.dist-info/WHEEL
fsim-0.0.5.dist-info/top_level.txt
fsim-0.0.5.dist-info/METADATA
fsim-0.0.5.data/scripts/fsim
