Metadata-Version: 2.1
Name: fsim
Version: 0.0.5
Home-page: https://github.com/Kuree/fsim
Author: Keyi Zhang
Author-email: keyi@cs.stanford.edu
License-File: LICENSE
Requires-Dist: ninja
